Workbook

Sheet Допущения
A1: Допущения (жёлтые ячейки можно менять — всё считается само)
A3: Параметр | B3: Старт | C3: Мастер | D3: Практик | E3: Комментарий
A4: Цена, ₽ | B4: 990 | C4: 4900 | D4: 14900 | E4: Цены в коде сайта после изменения
A5: Комиссия представителю, % от оплаты | B5: 0 | C5: 0.15 | D5: 0.15 | E5: Старт — воронка, процент не платим
A6: Фикс представителю за продажу, ₽ | B6: 100 | C6: 0 | D6: 0 | E6: Старт: символические 100 ₽ за привлечённого ученика
A7: Фикс представителю за проведённую практику, ₽ | B7: 0 | C7: 0 | D7: 2500 | E7: Выезд на объект, спецодежда, время наставника
A8: Себестоимость и поддержка на ученика, ₽ | B8: 50 | C8: 350 | D8: 1300 | E8: Старт: бот и поддержка; Мастер: проверка 14 фотоотчётов; Практик: + консультация автора 60 мин и расходные материалы
A9: Стоимость привлечения через платную рекламу (CAC), ₽ | B9: 400 | C9: 700 | D9: 2500 | E9: ПРОВЕРИТЬ на тестовой рекламе: пока оценка
A10: Доля тарифа среди клиентов, % | B10: 0.6 | C10: 0.3 | D10: 0.1 | E10: Итоговый микс 100 клиентов с учётом доплат с «Старта»
A12: Общие ставки | B12: Значение | E12: Комментарий
A13: Комиссия ЮKassa, % | B13: 0.035 | E13: Зависит от оборота и способа оплаты: у вас по договору, обычно 2,8–3,8%
A14: Налог УСН «Доходы», % | B14: 0.06 | E14: ДОПУЩЕНИЕ: ИП на УСН 6% с выручки. Если у вас НПД или другой режим — поменять
A15: Фонд рекламы и развития, % от выручки | B15: 0.2 | E15: Резерв на рекламу, контент, развитие
A16: Рекламный сбор 3% и ОРД | B16: 0 | E16: Платит получатель рекламных денег (блогер/представитель), вы только передаёте данные в ОРД; свои расходы на ОРД вписать при необходимости
A18: Страховые взносы ИП за себя (≈57 тыс. ₽/год + 1% с дохода свыше 300 тыс. ₽) в таблице не учтены — проверить актуальную сумму.

Sheet Юнит-экономика
A1: Что остаётся с одной продажи (на 1 клиента)
A3: Канал 1: продажа через регионального представителя (реклама не оплачивается, платим комиссию)
A4: Статья | B4: Старт | C4: Мастер | D4: Практик
A5: Цена | B5: =Допущения!B4 | C5: =Допущения!C4 | D5: =Допущения!D4
A6: − Комиссия ЮKassa | B6: =Допущения!B4*Допущения!$B$13 | C6: =Допущения!C4*Допущения!$B$13 | D6: =Допущения!D4*Допущения!$B$13
A7: − Налог УСН 6% | B7: =Допущения!B4*Допущения!$B$14 | C7: =Допущения!C4*Допущения!$B$14 | D7: =Допущения!D4*Допущения!$B$14
A8: − Комиссия представителю | B8: =Допущения!B4*Допущения!B5+Допущения!B6 | C8: =Допущения!C4*Допущения!C5+Допущения!C6 | D8: =Допущения!D4*Допущения!D5+Допущения!D6
A9: − Фикс за практику | B9: =Допущения!B7 | C9: =Допущения!C7 | D9: =Допущения!D7
A10: − Реклама (CAC) | B10: 0 | C10: 0 | D10: 0
A11: − Себестоимость и поддержка | B11: =Допущения!B8 | C11: =Допущения!C8 | D11: =Допущения!D8
A12: ОСТАЁТСЯ с продажи, ₽ | B12: =B5-SUM(B6:B11) | C12: =C5-SUM(C6:C11) | D12: =D5-SUM(D6:D11)
A13: Маржа, % | B13: =B12/B5 | C13: =C12/C5 | D13: =D12/D5
A15: Канал 2: платная реклама (без представителя; практику всё равно проводит наставник)
A16: Статья | B16: Старт | C16: Мастер | D16: Практик
A17: Цена | B17: =Допущения!B4 | C17: =Допущения!C4 | D17: =Допущения!D4
A18: − Комиссия ЮKassa | B18: =Допущения!B4*Допущения!$B$13 | C18: =Допущения!C4*Допущения!$B$13 | D18: =Допущения!D4*Допущения!$B$13
A19: − Налог УСН 6% | B19: =Допущения!B4*Допущения!$B$14 | C19: =Допущения!C4*Допущения!$B$14 | D19: =Допущения!D4*Допущения!$B$14
A20: − Комиссия представителю | B20: 0 | C20: 0 | D20: 0
A21: − Фикс за практику | B21: 0 | C21: 0 | D21: =Допущения!D7
A22: − Реклама (CAC) | B22: =Допущения!B9 | C22: =Допущения!C9 | D22: =Допущения!D9
A23: − Себестоимость и поддержка | B23: =Допущения!B8 | C23: =Допущения!C8 | D23: =Допущения!D8
A24: ОСТАЁТСЯ с продажи, ₽ | B24: =B17-SUM(B18:B23) | C24: =C17-SUM(C18:C23) | D24: =D17-SUM(D18:D23)
A25: Маржа, % | B25: =B24/B17 | C25: =C24/C17 | D25: =D24/D17

Sheet 100 клиентов
A1: Итог на 100 клиентов (через представителей) — выручка, налоги, прибыль
A3: Статья | B3: Старт | C3: Мастер | D3: Практик | E3: ИТОГО
A4: Клиентов | B4: =100*Допущения!B10 | C4: =100*Допущения!C10 | D4: =100*Допущения!D10 | E4: =SUM(B4:D4)
A5: Выручка | B5: =B4*'Юнит-экономика'!B5 | C5: =C4*'Юнит-экономика'!C5 | D5: =D4*'Юнит-экономика'!D5 | E5: =SUM(B5:D5)
A6: Остаётся после ЮKassa, налога, комиссий и поддержки | B6: =B4*'Юнит-экономика'!B10 | C6: =C4*'Юнит-экономика'!C10 | D6: =D4*'Юнит-экономика'!D10 | E6: =SUM(B6:D6)
A7: Из них налог УСН | B7: =B4*'Юнит-экономика'!B7 | C7: =C4*'Юнит-экономика'!C7 | D7: =D4*'Юнит-экономика'!D7 | E7: =SUM(B7:D7)
A8: Из них комиссия ЮKassa | B8: =B4*'Юнит-экономика'!B6 | C8: =C4*'Юнит-экономика'!C6 | D8: =D4*'Юнит-экономика'!D6 | E8: =SUM(B8:D8)
A9: Из них выплаты представителям | B9: =B4*('Юнит-экономика'!B8+'Юнит-экономика'!B9) | C9: =C4*('Юнит-экономика'!C8+'Юнит-экономика'!C9) | D9: =D4*('Юнит-экономика'!D8+'Юнит-экономика'!D9) | E9: =SUM(B9:D9)
A10: Фонд рекламы и развития (20% выручки) | B10: =B5*Допущения!$B$15 | C10: =C5*Допущения!$B$15 | D10: =D5*Допущения!$B$15 | E10: =SUM(B10:D10)
A11: Чистая прибыль до взносов ИП | B11: =B6-B10 | C11: =C6-C10 | D11: =D6-D10 | E11: =SUM(B11:D11)
A12: Чистая прибыль, % выручки | B12: =B11/B5 | C12: =C11/C5 | D12: =D11/D5 | E12: =E11/E5

Sheet Схема налогов и выплат
A1: Куда уходят деньги с каждой оплаты
A2: 1. Клиент платит на сайте → ЮKassa берёт комиссию эквайринга (≈3,5%) и переводит остаток на счёт ИП.
A3: 2. ИП платит налог УСН 6% со ВСЕЙ суммы оплаты (комиссия представителю налоговую базу не уменьшает на УСН «Доходы»).
A4: 3. Представителю выплачивается комиссия (% с продажи) и фикс за проведённую практику.
A5: • Оформление: договор + самозанятый (НПД) или ИП, чек «Мой налог» на каждую выплату. Налог с выплаты платит сам представитель.
A6: • Реферальные ссылки/промокоды — это реклама: нужен токен erid (ОРД), договор с представителем и передача данных по креативам.
A7: • Рекламный сбор 3% платит получатель рекламного дохода (блогер/представитель), а не вы — уточнить у бухгалтера порог и порядок.
A8: 4. Фонд рекламы и развития — 20% выручки откладывается отдельно (реклама, контент, видео, кураторы).
A9: 5. Что осталось — чистая прибыль до страховых взносов ИП (фиксированные взносы за себя + 1% с дохода свыше 300 тыс. ₽ в год).
A11: Воронка тарифов
A12: Старт 990 ₽ — вход и проверка интереса (почти без комиссии представителю).
A13: Доплата со «Старта»: до «Мастера» 3 910 ₽, до «Практика» 13 910 ₽ (с «Мастера» на «Практик» — 10 000 ₽).
... A17: Важно: всё выше — модель на допущениях. Реальный CAC, микс тарифов и режим налогообложения нужно подставить после первых продаж и проверить у бухгалтера.
